{
  "EPAFacilityID": "100000047932",
  "name": "Imperial, NE 5512",
  "state": "NE",
  "city": "Imperial",
  "address": "901 East Highway 6",
  "zip": "69033",
  "county_fips": "31029",
  "lat": 40.5322,
  "lng": -101.6569,
  "company_1": "Nutrien Ag Solutions",
  "company_2": "27760",
  "operator": "Nutrien Ag Solutions",
  "submissions": [
    {
      "id": 1000085266,
      "date": "2020-02-26",
      "name": "Imperial, NE 5512",
      "company_1": "Nutrien Ag Solutions",
      "company_2": "27760",
      "operator": "Nutrien Ag Solutions"
    },
    {
      "id": 1000078285,
      "date": "2019-07-03",
      "name": "Imperial, NE 5512",
      "company_1": "Nutrien Ag Solutions",
      "company_2": "27760",
      "operator": "Nutrien Ag Solutions"
    },
    {
      "id": 1000049588,
      "date": "2019-01-02",
      "name": "Imperial, NE 5512",
      "company_1": "Nutrien Ag Solutions",
      "company_2": "27760",
      "operator": "Nutrien Ag Solutions"
    },
    {
      "id": 1000021980,
      "date": "2014-04-15",
      "name": "Crop Production Services - Imperial, NE",
      "company_1": "Crop Production Services",
      "company_2": null,
      "operator": "Crop Production Services"
    },
    {
      "id": 1000021584,
      "date": "2011-04-15",
      "name": "Crop Production Services - Imperial, NE",
      "company_1": "Crop Production Services",
      "company_2": null,
      "operator": "Crop Production Services"
    },
    {
      "id": 48316,
      "date": "2007-05-22",
      "name": "UAP - Imperial, NE",
      "company_1": "UAP Distribution, Inc.",
      "company_2": null,
      "operator": "UAP Distribution, Inc."
    },
    {
      "id": 45485,
      "date": "2006-04-24",
      "name": "UAP - Imperial",
      "company_1": "UAP Distribution, Inc.",
      "company_2": null,
      "operator": "UAP Distribution, Inc."
    },
    {
      "id": 33820,
      "date": "2004-07-22",
      "name": "UAP Ag Service",
      "company_1": "UAP Pueblo",
      "company_2": null,
      "operator": "John Vogt"
    },
    {
      "id": 28037,
      "date": "2003-04-25",
      "name": "UAP Ag Service",
      "company_1": "UAP Pueblo",
      "company_2": null,
      "operator": "John Vogt"
    },
    {
      "id": 21600,
      "date": "2000-07-06",
      "name": "UAP Ag Service",
      "company_1": "UAP Pueblo",
      "company_2": null,
      "operator": "John Vogt"
    },
    {
      "id": 3879,
      "date": "1999-06-23",
      "name": "UAP Ag Service",
      "company_1": "UAP Pueblo",
      "company_2": null,
      "operator": "John Vogt"
    }
  ],
  "names_prev": [
    "Crop Production Services - Imperial, NE",
    "UAP - Imperial, NE",
    "UAP - Imperial",
    "UAP Ag Service"
  ]
}