{
  "EPAFacilityID": "100000077971",
  "name": "Helena Agri-Enterprises, LLC - Atlanta, IN Fac",
  "state": "IN",
  "city": "Atlanta",
  "ValidationDate": "2019-07-03",
  "address": "311 North Walnut",
  "zip": "46031",
  "county_fips": "18159",
  "company_1": null,
  "company_2": null,
  "operator": "Helena Agri-Enterprises, LLC",
  "submissions": [
    {
      "id": 1000081045,
      "date_rec": "2019-07-03",
      "date_val": "2019-07-03",
      "date_dereg": null,
      "lat_sub": "40.219469",
      "lon_sub": "-086.027161",
      "num_accidents": null,
      "latest_accident": null,
      "name": "Helena Agri-Enterprises, LLC - Atlanta, IN Fac",
      "company_1": null,
      "company_2": null,
      "operator": "Helena Agri-Enterprises, LLC"
    },
    {
      "id": 1000042985,
      "date_rec": "2014-05-27",
      "date_val": "2019-03-20",
      "date_dereg": null,
      "lat_sub": "40.215861",
      "lon_sub": "-086.243083",
      "num_accidents": null,
      "latest_accident": null,
      "name": "Helena Agri-Enterprises, LLC - Atlanta, IN Fac",
      "company_1": null,
      "company_2": null,
      "operator": "Helena Agri-Enterprises, LLC"
    },
    {
      "id": 55771,
      "date_rec": "2009-07-16",
      "date_val": "2009-07-17",
      "date_dereg": null,
      "lat_sub": "40.215861",
      "lon_sub": "-086.243083",
      "num_accidents": null,
      "latest_accident": null,
      "name": "Atlanta Crop Service Inc.",
      "company_1": null,
      "company_2": null,
      "operator": "Walter Shirk & Jane Meister"
    },
    {
      "id": 34196,
      "date_rec": "2004-06-21",
      "date_val": "2004-07-23",
      "date_dereg": null,
      "lat_sub": "40.219291",
      "lon_sub": "-086.027156",
      "num_accidents": null,
      "latest_accident": null,
      "name": "ATLANTA CROP SERVICE INC.",
      "company_1": null,
      "company_2": null,
      "operator": "Walter Shirk & Jane Meister"
    },
    {
      "id": 14671,
      "date_rec": "1999-07-15",
      "date_val": "1999-07-28",
      "date_dereg": null,
      "lat_sub": "40.22",
      "lon_sub": "-86.032778",
      "num_accidents": 1,
      "latest_accident": "1998-05-14",
      "name": "Atlanta Crop Service,Inc.",
      "company_1": null,
      "company_2": null,
      "operator": "Walter Shirk & Jane Meister"
    },
    {
      "id": 6168,
      "date_rec": "1999-06-21",
      "date_val": "1999-06-30",
      "date_dereg": null,
      "lat_sub": "40.22",
      "lon_sub": "-86.032778",
      "num_accidents": 1,
      "latest_accident": "1998-05-14",
      "name": "Atlanta Crop Service,Inc.",
      "company_1": null,
      "company_2": null,
      "operator": "Walter Shirk & Jane Meister"
    }
  ],
  "accidents": [
    {
      "id": 1919,
      "sub_id": 14671,
      "date": "1998-05-14",
      "time": "20:30",
      "chem": "Ammonia (anhydrous) \u2022 Ammonia (conc 20% or greater)",
      "deaths": 0,
      "inj": 0,
      "ev_shlt": 0,
      "damg": 0
    }
  ],
  "names_prev": [
    "Atlanta Crop Service Inc.",
    "ATLANTA CROP SERVICE INC.",
    "Atlanta Crop Service,Inc."
  ]
}