{
  "FacilityID": 1000107465,
  "FacilityName": "Matheson Tri-Gas - Newark, CA Branch",
  "FacilityStr1": "6775 Central Avenue",
  "FacilityStr2": null,
  "FacilityCity": "Newark",
  "FacilityState": "CA",
  "FacilityZipCode": "94560",
  "Facility4DigitZipExt": null,
  "FacilityCountyFIPS": "06001",
  "LEPC": "Region II, CA",
  "FacilityLatDecDegs": "37.526667",
  "FacilityLongDecDegs": "-122.028611",
  "ValidLatLongFlag": "Yes",
  "LatLongMethod": "I4",
  "LatLongDescription": "CE",
  "FacilityURL": "www.mathesongas.com",
  "FacilityEmailAddress": null,
  "FacilityDUNS": 106236144,
  "ParentCompanyName": "Taiyo Nippon Sanso Group",
  "Company2Name": null,
  "CompanyDUNS": null,
  "Company2DUNS": null,
  "OperatorName": "Matheson Tri-Gas, Inc.",
  "OperatorStr1": "1700 Scepter Road",
  "OperatorStr2": null,
  "OperatorCity": "Waverly",
  "OperatorStateFIPS": "TN",
  "OperatorZipCode": "37185",
  "OperatorZipCodeExt": null,
  "FTE": 41,
  "OtherEPAFacilityID": "CAD0-5304-6959",
  "EPAFacilityID": "100000148529",
  "OSHA_PSM": "Yes",
  "EPCRA_302": "Yes",
  "CAA_TitleV": "No",
  "ClearAirOpPermitID": null,
  "SafetyInspectionDate": "2023-09-07 00:00:00",
  "SafetyInspectionBy": "Alameda County Dept of Environmental Health",
  "OSHARanking": "No",
  "PredictiveFilingFlag": "No",
  "SubmissionType": "R",
  "RMPDescription": null,
  "NoAccidents": "No",
  "ForeignStateProv": null,
  "ForeignZipCode": null,
  "ForeignCountry": null,
  "CBI_Flag": "No",
  "CompletionCheckDate": "2023-10-13 00:00:00",
  "ErrorReportDate": null,
  "ReceiptDate": "2023-10-13 00:00:00",
  "GraphicsIndicator": "No",
  "AttachmentsIndicator": "No",
  "CertificationReceivedFlag": "Yes",
  "SubmissionMethod": "RMP*eSubmit",
  "CBISubstantiationFlag": "No",
  "ElectronicWaiverReceivedFlag": "No",
  "PostmarkDate": "2023-10-13 00:00:00",
  "RMPCompleteFlag": "Yes",
  "DeRegistrationDate": null,
  "DeRegistrationEffectiveDate": null,
  "AnniversaryDate": "2028-10-13 00:00:00",
  "CBIFlag": "No",
  "CBIUnsanitizedVersionFlag": "No",
  "VersionNumber": "1.0",
  "FRS_Lat": 37.526667,
  "FRS_Long": -122.028611,
  "FRS_Description": "CENTER OF FACILITY",
  "FRS_Method": "INTERPOLATION - DIGITAL MAP SRCE (TIGER)",
  "HorizontalAccMeasure": "25",
  "HorizontalRefDatumCode": "002",
  "SourceMapScaleNumber": null,
  "RMPSubmissionReasonCode": "R07",
  "DeregistrationReasonCode": null,
  "DeregistrationReasonOtherText": null,
  "_processes": [
    {
      "ProcessID": 1000134352,
      "AltID": "Bldg 7 CL2 Storage",
      "FacilityID": 1000107465,
      "ProgramLevel": 3,
      "CBI_Flag": "No",
      "_chemicals": [
        {
          "ProcessChemicalID": 1000168374,
          "ProcessID": 1000134352,
          "ChemicalID": 62,
          "Quantity": 14300.0,
          "CBI_Flag": "No",
          "_flam_mix_chemicals": []
        }
      ],
      "_naics": [
        {
          "Process_NAICS_ID": 1000135767,
          "ProcessID": 1000134352,
          "NAICSCode": "32512",
          "_prev_prog_3": [
            {
              "PreventionProgram3ID": 1000115740,
              "Process_NAICS_ID": 1000135767,
              "SafetyReviewDate": "2023-09-06 00:00:00",
              "PHA_Date": "2023-02-07 00:00:00",
              "PHA_WhatIf": "Yes",
              "PHA_Checklist": "Yes",
              "PHA_WhatIfChecklist": "No",
              "PHA_HAZOP": "No",
              "PHA_FMEA": "No",
              "PHA_FTA": "No",
              "PHA_OtherTechnique": null,
              "PHACompletionDate": "2022-03-15 00:00:00",
              "MH_ToxicRelease": "Yes",
              "MH_Fire": "Yes",
              "MH_Explosion": "Yes",
              "MH_RunawayReaction": "No",
              "MH_Polymerization": "No",
              "MH_Overpressurization": "Yes",
              "MH_Corrosion": "Yes",
              "MH_Overfilling": "No",
              "MH_Contamination": "No",
              "MH_EquipmentFailure": "Yes",
              "MH_CoolingLoss": "Yes",
              "MH_Earthquake": "Yes",
              "MH_Floods": "No",
              "MH_Tornado": "No",
              "MH_Hurricanes": "No",
              "MH_OtherType": null,
              "PC_Vents": "No",
              "PC_ReliefValves": "No",
              "PC_CheckValves": "No",
              "PC_Scrubbers": "No",
              "PC_Flares": "No",
              "PC_ManualShutoffs": "No",
              "PC_AutomaticShutoffs": "No",
              "PC_Interlocks": "No",
              "PC_Alarms": "Yes",
              "PC_KeyedBypass": "No",
              "PC_EmergencyAirSupply": "No",
              "PC_EmergencyPower": "Yes",
              "PC_BackupPump": "No",
              "PC_GroundingEquipment": "No",
              "PC_InhibitorAddition": "No",
              "PC_RuptureDisks": "No",
              "PC_ExcessFlowDevice": "No",
              "PC_QuenchSystem": "No",
              "PC_PurgeSystem": "No",
              "PC_None": "No",
              "PC_OtherType": "containment vessel, fusible plug",
              "MS_SprinklerSystem": "Yes",
              "MS_Dikes": "Yes",
              "MS_FireWalls": "Yes",
              "MS_BlastWalls": "No",
              "MS_DelugeSystem": "No",
              "MS_WaterCurtain": "No",
              "MS_Enclosure": "No",
              "MS_Neutralization": "No",
              "MS_None": "No",
              "MS_OtherType": "Canopy; Containment Vessel; Chlorine A&B Kit",
              "MD_ProcessAreaDetectors": "Yes",
              "MD_PerimeterMonitors": "No",
              "MD_None": "No",
              "MD_OtherType": "Life Safety System",
              "CH_ChemicalReduction": "No",
              "CH_ChemicalIncrease": "No",
              "CH_ChangeProcessParameters": "No",
              "CH_InstallProcessControls": "No",
              "CH_InstallProcessDetection": "No",
              "CH_InstallPerimeterMonitoring": "No",
              "CH_InstallMitigationSystems": "No",
              "CH_NoneRequired": "No",
              "CH_None": "Yes",
              "CH_OtherChanges": null,
              "OpProceduresReviewDate": "2022-12-14 00:00:00",
              "TrainingReviewDate": "2022-10-20 00:00:00",
              "TR_Classroom": "Yes",
              "TR_OnTheJob": "Yes",
              "TR_OtherType": "Intranet",
              "CT_WrittenTest": "Yes",
              "CT_OralTest": "No",
              "CT_Demonstration": "No",
              "CT_Observation": "Yes",
              "CT_OtherType": null,
              "MaintenanceReviewDate": "2022-10-20 00:00:00",
              "EquipmentInspectionDate": "2023-06-21 00:00:00",
              "EquipmentTested": "Gas detectors",
              "ChangeMgmtDate": "2020-02-14 00:00:00",
              "ChangeMgmtReviewDate": "2021-11-01 00:00:00",
              "PreStartupReviewDate": "2021-12-01 00:00:00",
              "ComplianceAuditDate": "2021-11-01 00:00:00",
              "AuditCompletionDate": "2023-05-24 00:00:00",
              "IncidentInvestigationDate": "2014-09-23 00:00:00",
              "InvestigationChangeDate": "2014-10-09 00:00:00",
              "ParticipationPlansReviewDate": "2021-11-01 00:00:00",
              "HotWorkPermitReviewDate": "2021-11-01 00:00:00",
              "ContractorSafetyReviewDate": "2023-01-17 00:00:00",
              "ContractorSafetyEvalDate": "2021-11-01 00:00:00",
              "CBI_Flag": "No",
              "Description": null,
              "_chemicals": [
                {
                  "PrimaryKey": 1000145198,
                  "PreventionProgram3ID": 1000115740,
                  "ProcessChemicalID": 1000168374
                }
              ]
            }
          ],
          "_prev_prog_2": []
        }
      ]
    },
    {
      "ProcessID": 1000134353,
      "AltID": "Bldg 5 H2Se Storage",
      "FacilityID": 1000107465,
      "ProgramLevel": 3,
      "CBI_Flag": "No",
      "_chemicals": [
        {
          "ProcessChemicalID": 1000168375,
          "ProcessID": 1000134353,
          "ChemicalID": 64,
          "Quantity": 2640.0,
          "CBI_Flag": "No",
          "_flam_mix_chemicals": []
        }
      ],
      "_naics": [
        {
          "Process_NAICS_ID": 1000135768,
          "ProcessID": 1000134353,
          "NAICSCode": "32512",
          "_prev_prog_3": [
            {
              "PreventionProgram3ID": 1000115741,
              "Process_NAICS_ID": 1000135768,
              "SafetyReviewDate": "2023-09-06 00:00:00",
              "PHA_Date": "2023-02-07 00:00:00",
              "PHA_WhatIf": "Yes",
              "PHA_Checklist": "Yes",
              "PHA_WhatIfChecklist": "No",
              "PHA_HAZOP": "No",
              "PHA_FMEA": "No",
              "PHA_FTA": "No",
              "PHA_OtherTechnique": null,
              "PHACompletionDate": "2022-03-15 00:00:00",
              "MH_ToxicRelease": "Yes",
              "MH_Fire": "Yes",
              "MH_Explosion": "Yes",
              "MH_RunawayReaction": "No",
              "MH_Polymerization": "No",
              "MH_Overpressurization": "Yes",
              "MH_Corrosion": "Yes",
              "MH_Overfilling": "No",
              "MH_Contamination": "No",
              "MH_EquipmentFailure": "Yes",
              "MH_CoolingLoss": "Yes",
              "MH_Earthquake": "Yes",
              "MH_Floods": "No",
              "MH_Tornado": "No",
              "MH_Hurricanes": "No",
              "MH_OtherType": null,
              "PC_Vents": "No",
              "PC_ReliefValves": "No",
              "PC_CheckValves": "No",
              "PC_Scrubbers": "No",
              "PC_Flares": "No",
              "PC_ManualShutoffs": "No",
              "PC_AutomaticShutoffs": "No",
              "PC_Interlocks": "No",
              "PC_Alarms": "Yes",
              "PC_KeyedBypass": "No",
              "PC_EmergencyAirSupply": "No",
              "PC_EmergencyPower": "Yes",
              "PC_BackupPump": "No",
              "PC_GroundingEquipment": "No",
              "PC_InhibitorAddition": "No",
              "PC_RuptureDisks": "No",
              "PC_ExcessFlowDevice": "No",
              "PC_QuenchSystem": "No",
              "PC_PurgeSystem": "No",
              "PC_None": "No",
              "PC_OtherType": "Fusible plug, containment vessel",
              "MS_SprinklerSystem": "Yes",
              "MS_Dikes": "Yes",
              "MS_FireWalls": "Yes",
              "MS_BlastWalls": "No",
              "MS_DelugeSystem": "No",
              "MS_WaterCurtain": "No",
              "MS_Enclosure": "No",
              "MS_Neutralization": "No",
              "MS_None": "No",
              "MS_OtherType": "Canopy, containment vessel",
              "MD_ProcessAreaDetectors": "Yes",
              "MD_PerimeterMonitors": "No",
              "MD_None": "No",
              "MD_OtherType": "Life safety system",
              "CH_ChemicalReduction": "No",
              "CH_ChemicalIncrease": "No",
              "CH_ChangeProcessParameters": "No",
              "CH_InstallProcessControls": "No",
              "CH_InstallProcessDetection": "No",
              "CH_InstallPerimeterMonitoring": "No",
              "CH_InstallMitigationSystems": "No",
              "CH_NoneRequired": "No",
              "CH_None": "Yes",
              "CH_OtherChanges": null,
              "OpProceduresReviewDate": "2022-12-14 00:00:00",
              "TrainingReviewDate": "2022-10-20 00:00:00",
              "TR_Classroom": "Yes",
              "TR_OnTheJob": "Yes",
              "TR_OtherType": null,
              "CT_WrittenTest": "Yes",
              "CT_OralTest": "No",
              "CT_Demonstration": "No",
              "CT_Observation": "Yes",
              "CT_OtherType": null,
              "MaintenanceReviewDate": "2022-10-20 00:00:00",
              "EquipmentInspectionDate": "2023-06-21 00:00:00",
              "EquipmentTested": "Gas detectors",
              "ChangeMgmtDate": "2020-02-14 00:00:00",
              "ChangeMgmtReviewDate": "2021-11-01 00:00:00",
              "PreStartupReviewDate": "2021-12-01 00:00:00",
              "ComplianceAuditDate": "2021-11-01 00:00:00",
              "AuditCompletionDate": "2023-05-24 00:00:00",
              "IncidentInvestigationDate": "2014-09-23 00:00:00",
              "InvestigationChangeDate": "2014-10-09 00:00:00",
              "ParticipationPlansReviewDate": "2021-11-01 00:00:00",
              "HotWorkPermitReviewDate": "2021-11-01 00:00:00",
              "ContractorSafetyReviewDate": "2023-01-17 00:00:00",
              "ContractorSafetyEvalDate": "2021-11-01 00:00:00",
              "CBI_Flag": "No",
              "Description": null,
              "_chemicals": [
                {
                  "PrimaryKey": 1000145212,
                  "PreventionProgram3ID": 1000115741,
                  "ProcessChemicalID": 1000168375
                }
              ]
            }
          ],
          "_prev_prog_2": []
        }
      ]
    },
    {
      "ProcessID": 1000134354,
      "AltID": "Bldg 7 NH3 Tonner Storage",
      "FacilityID": 1000107465,
      "ProgramLevel": 3,
      "CBI_Flag": "No",
      "_chemicals": [
        {
          "ProcessChemicalID": 1000168376,
          "ProcessID": 1000134354,
          "ChemicalID": 56,
          "Quantity": 67500.0,
          "CBI_Flag": "No",
          "_flam_mix_chemicals": []
        }
      ],
      "_naics": [
        {
          "Process_NAICS_ID": 1000135769,
          "ProcessID": 1000134354,
          "NAICSCode": "32512",
          "_prev_prog_3": [
            {
              "PreventionProgram3ID": 1000115744,
              "Process_NAICS_ID": 1000135769,
              "SafetyReviewDate": "2023-09-06 00:00:00",
              "PHA_Date": "2023-02-07 00:00:00",
              "PHA_WhatIf": "Yes",
              "PHA_Checklist": "Yes",
              "PHA_WhatIfChecklist": "No",
              "PHA_HAZOP": "No",
              "PHA_FMEA": "No",
              "PHA_FTA": "No",
              "PHA_OtherTechnique": null,
              "PHACompletionDate": "2022-03-15 00:00:00",
              "MH_ToxicRelease": "Yes",
              "MH_Fire": "Yes",
              "MH_Explosion": "Yes",
              "MH_RunawayReaction": "No",
              "MH_Polymerization": "No",
              "MH_Overpressurization": "Yes",
              "MH_Corrosion": "Yes",
              "MH_Overfilling": "No",
              "MH_Contamination": "No",
              "MH_EquipmentFailure": "Yes",
              "MH_CoolingLoss": "Yes",
              "MH_Earthquake": "Yes",
              "MH_Floods": "No",
              "MH_Tornado": "No",
              "MH_Hurricanes": "No",
              "MH_OtherType": null,
              "PC_Vents": "No",
              "PC_ReliefValves": "No",
              "PC_CheckValves": "No",
              "PC_Scrubbers": "No",
              "PC_Flares": "No",
              "PC_ManualShutoffs": "No",
              "PC_AutomaticShutoffs": "No",
              "PC_Interlocks": "No",
              "PC_Alarms": "Yes",
              "PC_KeyedBypass": "No",
              "PC_EmergencyAirSupply": "No",
              "PC_EmergencyPower": "Yes",
              "PC_BackupPump": "No",
              "PC_GroundingEquipment": "No",
              "PC_InhibitorAddition": "No",
              "PC_RuptureDisks": "No",
              "PC_ExcessFlowDevice": "No",
              "PC_QuenchSystem": "No",
              "PC_PurgeSystem": "No",
              "PC_None": "No",
              "PC_OtherType": "containment vessel, fusible plug",
              "MS_SprinklerSystem": "Yes",
              "MS_Dikes": "Yes",
              "MS_FireWalls": "Yes",
              "MS_BlastWalls": "No",
              "MS_DelugeSystem": "No",
              "MS_WaterCurtain": "No",
              "MS_Enclosure": "No",
              "MS_Neutralization": "No",
              "MS_None": "No",
              "MS_OtherType": "Canopy, containment vessel",
              "MD_ProcessAreaDetectors": "Yes",
              "MD_PerimeterMonitors": "No",
              "MD_None": "No",
              "MD_OtherType": "Life Safety System",
              "CH_ChemicalReduction": "No",
              "CH_ChemicalIncrease": "No",
              "CH_ChangeProcessParameters": "No",
              "CH_InstallProcessControls": "No",
              "CH_InstallProcessDetection": "No",
              "CH_InstallPerimeterMonitoring": "No",
              "CH_InstallMitigationSystems": "No",
              "CH_NoneRequired": "No",
              "CH_None": "Yes",
              "CH_OtherChanges": null,
              "OpProceduresReviewDate": "2022-12-14 00:00:00",
              "TrainingReviewDate": "2022-10-20 00:00:00",
              "TR_Classroom": "Yes",
              "TR_OnTheJob": "Yes",
              "TR_OtherType": "Intranet",
              "CT_WrittenTest": "Yes",
              "CT_OralTest": "No",
              "CT_Demonstration": "No",
              "CT_Observation": "Yes",
              "CT_OtherType": null,
              "MaintenanceReviewDate": "2022-10-20 00:00:00",
              "EquipmentInspectionDate": "2023-06-21 00:00:00",
              "EquipmentTested": "Gas detectors",
              "ChangeMgmtDate": "2020-02-14 00:00:00",
              "ChangeMgmtReviewDate": "2021-11-01 00:00:00",
              "PreStartupReviewDate": "2021-12-01 00:00:00",
              "ComplianceAuditDate": "2021-11-01 00:00:00",
              "AuditCompletionDate": "2023-05-24 00:00:00",
              "IncidentInvestigationDate": "2014-09-23 00:00:00",
              "InvestigationChangeDate": "2014-10-09 00:00:00",
              "ParticipationPlansReviewDate": "2021-11-01 00:00:00",
              "HotWorkPermitReviewDate": "2021-11-01 00:00:00",
              "ContractorSafetyReviewDate": "2023-01-17 00:00:00",
              "ContractorSafetyEvalDate": "2021-11-01 00:00:00",
              "CBI_Flag": "No",
              "Description": null,
              "_chemicals": [
                {
                  "PrimaryKey": 1000145199,
                  "PreventionProgram3ID": 1000115744,
                  "ProcessChemicalID": 1000168376
                }
              ]
            }
          ],
          "_prev_prog_2": []
        }
      ]
    },
    {
      "ProcessID": 1000134355,
      "AltID": "Bldg 5 NH3 Storage",
      "FacilityID": 1000107465,
      "ProgramLevel": 3,
      "CBI_Flag": "No",
      "_chemicals": [
        {
          "ProcessChemicalID": 1000168377,
          "ProcessID": 1000134355,
          "ChemicalID": 56,
          "Quantity": 30000.0,
          "CBI_Flag": "No",
          "_flam_mix_chemicals": []
        }
      ],
      "_naics": [
        {
          "Process_NAICS_ID": 1000135770,
          "ProcessID": 1000134355,
          "NAICSCode": "32512",
          "_prev_prog_3": [
            {
              "PreventionProgram3ID": 1000115745,
              "Process_NAICS_ID": 1000135770,
              "SafetyReviewDate": "2023-09-06 00:00:00",
              "PHA_Date": "2023-02-07 00:00:00",
              "PHA_WhatIf": "Yes",
              "PHA_Checklist": "Yes",
              "PHA_WhatIfChecklist": "No",
              "PHA_HAZOP": "No",
              "PHA_FMEA": "No",
              "PHA_FTA": "No",
              "PHA_OtherTechnique": null,
              "PHACompletionDate": "2022-03-15 00:00:00",
              "MH_ToxicRelease": "Yes",
              "MH_Fire": "Yes",
              "MH_Explosion": "Yes",
              "MH_RunawayReaction": "No",
              "MH_Polymerization": "No",
              "MH_Overpressurization": "Yes",
              "MH_Corrosion": "Yes",
              "MH_Overfilling": "No",
              "MH_Contamination": "No",
              "MH_EquipmentFailure": "Yes",
              "MH_CoolingLoss": "Yes",
              "MH_Earthquake": "Yes",
              "MH_Floods": "No",
              "MH_Tornado": "No",
              "MH_Hurricanes": "No",
              "MH_OtherType": null,
              "PC_Vents": "No",
              "PC_ReliefValves": "No",
              "PC_CheckValves": "No",
              "PC_Scrubbers": "No",
              "PC_Flares": "No",
              "PC_ManualShutoffs": "No",
              "PC_AutomaticShutoffs": "No",
              "PC_Interlocks": "No",
              "PC_Alarms": "Yes",
              "PC_KeyedBypass": "No",
              "PC_EmergencyAirSupply": "No",
              "PC_EmergencyPower": "Yes",
              "PC_BackupPump": "No",
              "PC_GroundingEquipment": "No",
              "PC_InhibitorAddition": "No",
              "PC_RuptureDisks": "No",
              "PC_ExcessFlowDevice": "No",
              "PC_QuenchSystem": "No",
              "PC_PurgeSystem": "No",
              "PC_None": "No",
              "PC_OtherType": "containment vessel, fusible plug",
              "MS_SprinklerSystem": "Yes",
              "MS_Dikes": "Yes",
              "MS_FireWalls": "Yes",
              "MS_BlastWalls": "No",
              "MS_DelugeSystem": "No",
              "MS_WaterCurtain": "No",
              "MS_Enclosure": "No",
              "MS_Neutralization": "No",
              "MS_None": "No",
              "MS_OtherType": "Canopy, containment vessel",
              "MD_ProcessAreaDetectors": "Yes",
              "MD_PerimeterMonitors": "No",
              "MD_None": "No",
              "MD_OtherType": "Life Safety System",
              "CH_ChemicalReduction": "No",
              "CH_ChemicalIncrease": "No",
              "CH_ChangeProcessParameters": "No",
              "CH_InstallProcessControls": "No",
              "CH_InstallProcessDetection": "No",
              "CH_InstallPerimeterMonitoring": "No",
              "CH_InstallMitigationSystems": "No",
              "CH_NoneRequired": "No",
              "CH_None": "Yes",
              "CH_OtherChanges": null,
              "OpProceduresReviewDate": "2022-12-14 00:00:00",
              "TrainingReviewDate": "2022-10-20 00:00:00",
              "TR_Classroom": "Yes",
              "TR_OnTheJob": "Yes",
              "TR_OtherType": "Intranet",
              "CT_WrittenTest": "Yes",
              "CT_OralTest": "No",
              "CT_Demonstration": "No",
              "CT_Observation": "Yes",
              "CT_OtherType": null,
              "MaintenanceReviewDate": "2022-10-20 00:00:00",
              "EquipmentInspectionDate": "2023-06-21 00:00:00",
              "EquipmentTested": "Gas detectors",
              "ChangeMgmtDate": "2020-02-14 00:00:00",
              "ChangeMgmtReviewDate": "2021-11-01 00:00:00",
              "PreStartupReviewDate": "2021-12-01 00:00:00",
              "ComplianceAuditDate": "2021-11-01 00:00:00",
              "AuditCompletionDate": "2023-05-24 00:00:00",
              "IncidentInvestigationDate": "2014-09-23 00:00:00",
              "InvestigationChangeDate": "2014-10-09 00:00:00",
              "ParticipationPlansReviewDate": "2021-11-01 00:00:00",
              "HotWorkPermitReviewDate": "2021-11-01 00:00:00",
              "ContractorSafetyReviewDate": "2023-01-17 00:00:00",
              "ContractorSafetyEvalDate": "2021-11-01 00:00:00",
              "CBI_Flag": "No",
              "Description": null,
              "_chemicals": [
                {
                  "PrimaryKey": 1000145200,
                  "PreventionProgram3ID": 1000115745,
                  "ProcessChemicalID": 1000168377
                }
              ]
            }
          ],
          "_prev_prog_2": []
        }
      ]
    },
    {
      "ProcessID": 1000134356,
      "AltID": "Bldg 7 AsH3 Cyl Storage",
      "FacilityID": 1000107465,
      "ProgramLevel": 3,
      "CBI_Flag": "No",
      "_chemicals": [
        {
          "ProcessChemicalID": 1000168378,
          "ProcessID": 1000134356,
          "ChemicalID": 67,
          "Quantity": 5100.0,
          "CBI_Flag": "No",
          "_flam_mix_chemicals": []
        }
      ],
      "_naics": [
        {
          "Process_NAICS_ID": 1000135771,
          "ProcessID": 1000134356,
          "NAICSCode": "32512",
          "_prev_prog_3": [
            {
              "PreventionProgram3ID": 1000115746,
              "Process_NAICS_ID": 1000135771,
              "SafetyReviewDate": "2023-09-06 00:00:00",
              "PHA_Date": "2023-02-07 00:00:00",
              "PHA_WhatIf": "Yes",
              "PHA_Checklist": "Yes",
              "PHA_WhatIfChecklist": "No",
              "PHA_HAZOP": "No",
              "PHA_FMEA": "No",
              "PHA_FTA": "No",
              "PHA_OtherTechnique": null,
              "PHACompletionDate": "2022-03-15 00:00:00",
              "MH_ToxicRelease": "Yes",
              "MH_Fire": "Yes",
              "MH_Explosion": "Yes",
              "MH_RunawayReaction": "No",
              "MH_Polymerization": "No",
              "MH_Overpressurization": "Yes",
              "MH_Corrosion": "Yes",
              "MH_Overfilling": "No",
              "MH_Contamination": "No",
              "MH_EquipmentFailure": "Yes",
              "MH_CoolingLoss": "Yes",
              "MH_Earthquake": "Yes",
              "MH_Floods": "No",
              "MH_Tornado": "No",
              "MH_Hurricanes": "No",
              "MH_OtherType": null,
              "PC_Vents": "No",
              "PC_ReliefValves": "No",
              "PC_CheckValves": "No",
              "PC_Scrubbers": "No",
              "PC_Flares": "No",
              "PC_ManualShutoffs": "No",
              "PC_AutomaticShutoffs": "No",
              "PC_Interlocks": "No",
              "PC_Alarms": "Yes",
              "PC_KeyedBypass": "No",
              "PC_EmergencyAirSupply": "No",
              "PC_EmergencyPower": "Yes",
              "PC_BackupPump": "No",
              "PC_GroundingEquipment": "No",
              "PC_InhibitorAddition": "No",
              "PC_RuptureDisks": "No",
              "PC_ExcessFlowDevice": "No",
              "PC_QuenchSystem": "No",
              "PC_PurgeSystem": "No",
              "PC_None": "No",
              "PC_OtherType": "containment vessel, fusible plug",
              "MS_SprinklerSystem": "Yes",
              "MS_Dikes": "Yes",
              "MS_FireWalls": "Yes",
              "MS_BlastWalls": "No",
              "MS_DelugeSystem": "No",
              "MS_WaterCurtain": "No",
              "MS_Enclosure": "No",
              "MS_Neutralization": "No",
              "MS_None": "No",
              "MS_OtherType": "containment vessel",
              "MD_ProcessAreaDetectors": "Yes",
              "MD_PerimeterMonitors": "No",
              "MD_None": "No",
              "MD_OtherType": "Life Safety System",
              "CH_ChemicalReduction": "No",
              "CH_ChemicalIncrease": "No",
              "CH_ChangeProcessParameters": "No",
              "CH_InstallProcessControls": "No",
              "CH_InstallProcessDetection": "No",
              "CH_InstallPerimeterMonitoring": "No",
              "CH_InstallMitigationSystems": "No",
              "CH_NoneRequired": "No",
              "CH_None": "Yes",
              "CH_OtherChanges": null,
              "OpProceduresReviewDate": "2022-12-14 00:00:00",
              "TrainingReviewDate": "2022-10-20 00:00:00",
              "TR_Classroom": "Yes",
              "TR_OnTheJob": "Yes",
              "TR_OtherType": "Intranet",
              "CT_WrittenTest": "Yes",
              "CT_OralTest": "No",
              "CT_Demonstration": "No",
              "CT_Observation": "Yes",
              "CT_OtherType": null,
              "MaintenanceReviewDate": "2022-10-20 00:00:00",
              "EquipmentInspectionDate": "2023-06-21 00:00:00",
              "EquipmentTested": "Gas detectors",
              "ChangeMgmtDate": "2020-02-14 00:00:00",
              "ChangeMgmtReviewDate": "2021-11-01 00:00:00",
              "PreStartupReviewDate": "2021-12-01 00:00:00",
              "ComplianceAuditDate": "2021-11-01 00:00:00",
              "AuditCompletionDate": "2023-05-24 00:00:00",
              "IncidentInvestigationDate": "2014-09-23 00:00:00",
              "InvestigationChangeDate": "2014-10-09 00:00:00",
              "ParticipationPlansReviewDate": "2021-11-01 00:00:00",
              "HotWorkPermitReviewDate": "2021-11-01 00:00:00",
              "ContractorSafetyReviewDate": "2023-01-17 00:00:00",
              "ContractorSafetyEvalDate": "2021-11-01 00:00:00",
              "CBI_Flag": "No",
              "Description": null,
              "_chemicals": [
                {
                  "PrimaryKey": 1000145201,
                  "PreventionProgram3ID": 1000115746,
                  "ProcessChemicalID": 1000168378
                }
              ]
            }
          ],
          "_prev_prog_2": []
        }
      ]
    },
    {
      "ProcessID": 1000134357,
      "AltID": "Bldg 5 Cl2 Storage",
      "FacilityID": 1000107465,
      "ProgramLevel": 3,
      "CBI_Flag": "No",
      "_chemicals": [
        {
          "ProcessChemicalID": 1000168379,
          "ProcessID": 1000134357,
          "ChemicalID": 62,
          "Quantity": 22000.0,
          "CBI_Flag": "No",
          "_flam_mix_chemicals": []
        }
      ],
      "_naics": [
        {
          "Process_NAICS_ID": 1000135772,
          "ProcessID": 1000134357,
          "NAICSCode": "32512",
          "_prev_prog_3": [
            {
              "PreventionProgram3ID": 1000115747,
              "Process_NAICS_ID": 1000135772,
              "SafetyReviewDate": "2023-09-06 00:00:00",
              "PHA_Date": "2023-02-07 00:00:00",
              "PHA_WhatIf": "Yes",
              "PHA_Checklist": "Yes",
              "PHA_WhatIfChecklist": "No",
              "PHA_HAZOP": "No",
              "PHA_FMEA": "No",
              "PHA_FTA": "No",
              "PHA_OtherTechnique": null,
              "PHACompletionDate": "2022-03-15 00:00:00",
              "MH_ToxicRelease": "Yes",
              "MH_Fire": "Yes",
              "MH_Explosion": "Yes",
              "MH_RunawayReaction": "No",
              "MH_Polymerization": "No",
              "MH_Overpressurization": "Yes",
              "MH_Corrosion": "Yes",
              "MH_Overfilling": "No",
              "MH_Contamination": "No",
              "MH_EquipmentFailure": "Yes",
              "MH_CoolingLoss": "Yes",
              "MH_Earthquake": "Yes",
              "MH_Floods": "No",
              "MH_Tornado": "No",
              "MH_Hurricanes": "No",
              "MH_OtherType": null,
              "PC_Vents": "No",
              "PC_ReliefValves": "No",
              "PC_CheckValves": "No",
              "PC_Scrubbers": "No",
              "PC_Flares": "No",
              "PC_ManualShutoffs": "No",
              "PC_AutomaticShutoffs": "No",
              "PC_Interlocks": "No",
              "PC_Alarms": "Yes",
              "PC_KeyedBypass": "No",
              "PC_EmergencyAirSupply": "No",
              "PC_EmergencyPower": "Yes",
              "PC_BackupPump": "No",
              "PC_GroundingEquipment": "No",
              "PC_InhibitorAddition": "No",
              "PC_RuptureDisks": "No",
              "PC_ExcessFlowDevice": "No",
              "PC_QuenchSystem": "No",
              "PC_PurgeSystem": "No",
              "PC_None": "No",
              "PC_OtherType": "containment vessel, fusible plug",
              "MS_SprinklerSystem": "Yes",
              "MS_Dikes": "Yes",
              "MS_FireWalls": "Yes",
              "MS_BlastWalls": "No",
              "MS_DelugeSystem": "No",
              "MS_WaterCurtain": "No",
              "MS_Enclosure": "No",
              "MS_Neutralization": "No",
              "MS_None": "No",
              "MS_OtherType": "Canopy; Containment Vessel; Chlorine A&B Kit",
              "MD_ProcessAreaDetectors": "Yes",
              "MD_PerimeterMonitors": "No",
              "MD_None": "No",
              "MD_OtherType": "Life Safety System",
              "CH_ChemicalReduction": "No",
              "CH_ChemicalIncrease": "No",
              "CH_ChangeProcessParameters": "No",
              "CH_InstallProcessControls": "No",
              "CH_InstallProcessDetection": "No",
              "CH_InstallPerimeterMonitoring": "No",
              "CH_InstallMitigationSystems": "No",
              "CH_NoneRequired": "No",
              "CH_None": "Yes",
              "CH_OtherChanges": null,
              "OpProceduresReviewDate": "2022-12-14 00:00:00",
              "TrainingReviewDate": "2022-10-20 00:00:00",
              "TR_Classroom": "Yes",
              "TR_OnTheJob": "Yes",
              "TR_OtherType": "Intranet",
              "CT_WrittenTest": "Yes",
              "CT_OralTest": "No",
              "CT_Demonstration": "No",
              "CT_Observation": "Yes",
              "CT_OtherType": null,
              "MaintenanceReviewDate": "2022-10-20 00:00:00",
              "EquipmentInspectionDate": "2023-06-21 00:00:00",
              "EquipmentTested": "Gas detectors",
              "ChangeMgmtDate": "2020-02-14 00:00:00",
              "ChangeMgmtReviewDate": "2021-11-01 00:00:00",
              "PreStartupReviewDate": "2021-12-01 00:00:00",
              "ComplianceAuditDate": "2021-11-01 00:00:00",
              "AuditCompletionDate": "2023-05-24 00:00:00",
              "IncidentInvestigationDate": "2014-09-23 00:00:00",
              "InvestigationChangeDate": "2014-10-09 00:00:00",
              "ParticipationPlansReviewDate": "2021-11-01 00:00:00",
              "HotWorkPermitReviewDate": "2021-11-01 00:00:00",
              "ContractorSafetyReviewDate": "2023-01-17 00:00:00",
              "ContractorSafetyEvalDate": "2021-11-01 00:00:00",
              "CBI_Flag": "No",
              "Description": null,
              "_chemicals": [
                {
                  "PrimaryKey": 1000145202,
                  "PreventionProgram3ID": 1000115747,
                  "ProcessChemicalID": 1000168379
                }
              ]
            }
          ],
          "_prev_prog_2": []
        }
      ]
    },
    {
      "ProcessID": 1000134358,
      "AltID": "Bldg 7 HF Storage",
      "FacilityID": 1000107465,
      "ProgramLevel": 3,
      "CBI_Flag": "No",
      "_chemicals": [
        {
          "ProcessChemicalID": 1000168380,
          "ProcessID": 1000134358,
          "ChemicalID": 55,
          "Quantity": 5000.0,
          "CBI_Flag": "No",
          "_flam_mix_chemicals": []
        }
      ],
      "_naics": [
        {
          "Process_NAICS_ID": 1000135773,
          "ProcessID": 1000134358,
          "NAICSCode": "32512",
          "_prev_prog_3": [
            {
              "PreventionProgram3ID": 1000115748,
              "Process_NAICS_ID": 1000135773,
              "SafetyReviewDate": "2023-09-06 00:00:00",
              "PHA_Date": "2023-02-07 00:00:00",
              "PHA_WhatIf": "Yes",
              "PHA_Checklist": "Yes",
              "PHA_WhatIfChecklist": "No",
              "PHA_HAZOP": "No",
              "PHA_FMEA": "No",
              "PHA_FTA": "No",
              "PHA_OtherTechnique": null,
              "PHACompletionDate": "2022-03-15 00:00:00",
              "MH_ToxicRelease": "Yes",
              "MH_Fire": "Yes",
              "MH_Explosion": "Yes",
              "MH_RunawayReaction": "No",
              "MH_Polymerization": "No",
              "MH_Overpressurization": "Yes",
              "MH_Corrosion": "Yes",
              "MH_Overfilling": "No",
              "MH_Contamination": "No",
              "MH_EquipmentFailure": "Yes",
              "MH_CoolingLoss": "Yes",
              "MH_Earthquake": "Yes",
              "MH_Floods": "No",
              "MH_Tornado": "No",
              "MH_Hurricanes": "No",
              "MH_OtherType": null,
              "PC_Vents": "No",
              "PC_ReliefValves": "No",
              "PC_CheckValves": "No",
              "PC_Scrubbers": "No",
              "PC_Flares": "No",
              "PC_ManualShutoffs": "No",
              "PC_AutomaticShutoffs": "No",
              "PC_Interlocks": "No",
              "PC_Alarms": "Yes",
              "PC_KeyedBypass": "No",
              "PC_EmergencyAirSupply": "No",
              "PC_EmergencyPower": "Yes",
              "PC_BackupPump": "No",
              "PC_GroundingEquipment": "No",
              "PC_InhibitorAddition": "No",
              "PC_RuptureDisks": "No",
              "PC_ExcessFlowDevice": "No",
              "PC_QuenchSystem": "No",
              "PC_PurgeSystem": "No",
              "PC_None": "No",
              "PC_OtherType": "containment vessel, fusible plug",
              "MS_SprinklerSystem": "Yes",
              "MS_Dikes": "Yes",
              "MS_FireWalls": "Yes",
              "MS_BlastWalls": "No",
              "MS_DelugeSystem": "No",
              "MS_WaterCurtain": "No",
              "MS_Enclosure": "No",
              "MS_Neutralization": "No",
              "MS_None": "No",
              "MS_OtherType": "Canopy; Containment Vessel",
              "MD_ProcessAreaDetectors": "Yes",
              "MD_PerimeterMonitors": "No",
              "MD_None": "No",
              "MD_OtherType": "Life Safety System",
              "CH_ChemicalReduction": "No",
              "CH_ChemicalIncrease": "No",
              "CH_ChangeProcessParameters": "No",
              "CH_InstallProcessControls": "No",
              "CH_InstallProcessDetection": "No",
              "CH_InstallPerimeterMonitoring": "No",
              "CH_InstallMitigationSystems": "No",
              "CH_NoneRequired": "No",
              "CH_None": "Yes",
              "CH_OtherChanges": null,
              "OpProceduresReviewDate": "2022-12-14 00:00:00",
              "TrainingReviewDate": "2022-10-20 00:00:00",
              "TR_Classroom": "Yes",
              "TR_OnTheJob": "Yes",
              "TR_OtherType": "Intranet",
              "CT_WrittenTest": "Yes",
              "CT_OralTest": "No",
              "CT_Demonstration": "No",
              "CT_Observation": "Yes",
              "CT_OtherType": null,
              "MaintenanceReviewDate": "2022-10-20 00:00:00",
              "EquipmentInspectionDate": "2023-06-21 00:00:00",
              "EquipmentTested": "Gas detectors",
              "ChangeMgmtDate": "2020-02-14 00:00:00",
              "ChangeMgmtReviewDate": "2021-11-01 00:00:00",
              "PreStartupReviewDate": "2021-12-01 00:00:00",
              "ComplianceAuditDate": "2021-11-01 00:00:00",
              "AuditCompletionDate": "2023-05-24 00:00:00",
              "IncidentInvestigationDate": "2014-09-23 00:00:00",
              "InvestigationChangeDate": "2014-10-09 00:00:00",
              "ParticipationPlansReviewDate": "2021-11-01 00:00:00",
              "HotWorkPermitReviewDate": "2021-11-01 00:00:00",
              "ContractorSafetyReviewDate": "2023-01-17 00:00:00",
              "ContractorSafetyEvalDate": "2021-11-01 00:00:00",
              "CBI_Flag": "No",
              "Description": null,
              "_chemicals": [
                {
                  "PrimaryKey": 1000145203,
                  "PreventionProgram3ID": 1000115748,
                  "ProcessChemicalID": 1000168380
                }
              ]
            }
          ],
          "_prev_prog_2": []
        }
      ]
    },
    {
      "ProcessID": 1000134359,
      "AltID": "Bldg 5 HCl  Storage",
      "FacilityID": 1000107465,
      "ProgramLevel": 3,
      "CBI_Flag": "No",
      "_chemicals": [
        {
          "ProcessChemicalID": 1000168381,
          "ProcessID": 1000134359,
          "ChemicalID": 54,
          "Quantity": 40000.0,
          "CBI_Flag": "No",
          "_flam_mix_chemicals": []
        }
      ],
      "_naics": [
        {
          "Process_NAICS_ID": 1000135774,
          "ProcessID": 1000134359,
          "NAICSCode": "32512",
          "_prev_prog_3": [
            {
              "PreventionProgram3ID": 1000115749,
              "Process_NAICS_ID": 1000135774,
              "SafetyReviewDate": "2023-09-06 00:00:00",
              "PHA_Date": "2023-02-07 00:00:00",
              "PHA_WhatIf": "Yes",
              "PHA_Checklist": "Yes",
              "PHA_WhatIfChecklist": "No",
              "PHA_HAZOP": "No",
              "PHA_FMEA": "No",
              "PHA_FTA": "No",
              "PHA_OtherTechnique": null,
              "PHACompletionDate": "2022-03-15 00:00:00",
              "MH_ToxicRelease": "Yes",
              "MH_Fire": "Yes",
              "MH_Explosion": "Yes",
              "MH_RunawayReaction": "No",
              "MH_Polymerization": "No",
              "MH_Overpressurization": "Yes",
              "MH_Corrosion": "Yes",
              "MH_Overfilling": "No",
              "MH_Contamination": "No",
              "MH_EquipmentFailure": "Yes",
              "MH_CoolingLoss": "Yes",
              "MH_Earthquake": "Yes",
              "MH_Floods": "No",
              "MH_Tornado": "No",
              "MH_Hurricanes": "No",
              "MH_OtherType": null,
              "PC_Vents": "No",
              "PC_ReliefValves": "No",
              "PC_CheckValves": "No",
              "PC_Scrubbers": "No",
              "PC_Flares": "No",
              "PC_ManualShutoffs": "No",
              "PC_AutomaticShutoffs": "No",
              "PC_Interlocks": "No",
              "PC_Alarms": "Yes",
              "PC_KeyedBypass": "No",
              "PC_EmergencyAirSupply": "No",
              "PC_EmergencyPower": "Yes",
              "PC_BackupPump": "No",
              "PC_GroundingEquipment": "No",
              "PC_InhibitorAddition": "No",
              "PC_RuptureDisks": "No",
              "PC_ExcessFlowDevice": "No",
              "PC_QuenchSystem": "No",
              "PC_PurgeSystem": "No",
              "PC_None": "No",
              "PC_OtherType": "containment vessel, fusible plug",
              "MS_SprinklerSystem": "Yes",
              "MS_Dikes": "Yes",
              "MS_FireWalls": "Yes",
              "MS_BlastWalls": "No",
              "MS_DelugeSystem": "No",
              "MS_WaterCurtain": "No",
              "MS_Enclosure": "No",
              "MS_Neutralization": "No",
              "MS_None": "No",
              "MS_OtherType": "Canopy; Containment Vessel",
              "MD_ProcessAreaDetectors": "Yes",
              "MD_PerimeterMonitors": "No",
              "MD_None": "No",
              "MD_OtherType": "Life Safety System",
              "CH_ChemicalReduction": "No",
              "CH_ChemicalIncrease": "No",
              "CH_ChangeProcessParameters": "No",
              "CH_InstallProcessControls": "No",
              "CH_InstallProcessDetection": "No",
              "CH_InstallPerimeterMonitoring": "No",
              "CH_InstallMitigationSystems": "No",
              "CH_NoneRequired": "No",
              "CH_None": "Yes",
              "CH_OtherChanges": null,
              "OpProceduresReviewDate": "2022-12-14 00:00:00",
              "TrainingReviewDate": "2022-10-20 00:00:00",
              "TR_Classroom": "Yes",
              "TR_OnTheJob": "Yes",
              "TR_OtherType": "Intranet",
              "CT_WrittenTest": "Yes",
              "CT_OralTest": "No",
              "CT_Demonstration": "No",
              "CT_Observation": "Yes",
              "CT_OtherType": null,
              "MaintenanceReviewDate": "2022-10-20 00:00:00",
              "EquipmentInspectionDate": "2023-06-21 00:00:00",
              "EquipmentTested": "Gas detectors",
              "ChangeMgmtDate": "2020-02-14 00:00:00",
              "ChangeMgmtReviewDate": "2021-11-01 00:00:00",
              "PreStartupReviewDate": "2021-12-01 00:00:00",
              "ComplianceAuditDate": "2021-11-01 00:00:00",
              "AuditCompletionDate": "2023-05-24 00:00:00",
              "IncidentInvestigationDate": "2014-09-23 00:00:00",
              "InvestigationChangeDate": "2014-10-09 00:00:00",
              "ParticipationPlansReviewDate": "2021-11-01 00:00:00",
              "HotWorkPermitReviewDate": "2021-11-01 00:00:00",
              "ContractorSafetyReviewDate": "2023-01-17 00:00:00",
              "ContractorSafetyEvalDate": "2021-11-01 00:00:00",
              "CBI_Flag": "No",
              "Description": null,
              "_chemicals": [
                {
                  "PrimaryKey": 1000145204,
                  "PreventionProgram3ID": 1000115749,
                  "ProcessChemicalID": 1000168381
                }
              ]
            }
          ],
          "_prev_prog_2": []
        }
      ]
    },
    {
      "ProcessID": 1000134360,
      "AltID": "Bldg 7 Cl3HSi Pod Storage",
      "FacilityID": 1000107465,
      "ProgramLevel": 3,
      "CBI_Flag": "No",
      "_chemicals": [
        {
          "ProcessChemicalID": 1000168382,
          "ProcessID": 1000134360,
          "ChemicalID": 153,
          "Quantity": 15000.0,
          "CBI_Flag": "No",
          "_flam_mix_chemicals": []
        }
      ],
      "_naics": [
        {
          "Process_NAICS_ID": 1000135775,
          "ProcessID": 1000134360,
          "NAICSCode": "32512",
          "_prev_prog_3": [
            {
              "PreventionProgram3ID": 1000115750,
              "Process_NAICS_ID": 1000135775,
              "SafetyReviewDate": "2023-09-06 00:00:00",
              "PHA_Date": "2023-02-07 00:00:00",
              "PHA_WhatIf": "Yes",
              "PHA_Checklist": "Yes",
              "PHA_WhatIfChecklist": "No",
              "PHA_HAZOP": "No",
              "PHA_FMEA": "No",
              "PHA_FTA": "No",
              "PHA_OtherTechnique": null,
              "PHACompletionDate": "2022-03-15 00:00:00",
              "MH_ToxicRelease": "Yes",
              "MH_Fire": "Yes",
              "MH_Explosion": "Yes",
              "MH_RunawayReaction": "No",
              "MH_Polymerization": "No",
              "MH_Overpressurization": "Yes",
              "MH_Corrosion": "Yes",
              "MH_Overfilling": "No",
              "MH_Contamination": "No",
              "MH_EquipmentFailure": "Yes",
              "MH_CoolingLoss": "Yes",
              "MH_Earthquake": "Yes",
              "MH_Floods": "No",
              "MH_Tornado": "No",
              "MH_Hurricanes": "No",
              "MH_OtherType": null,
              "PC_Vents": "No",
              "PC_ReliefValves": "No",
              "PC_CheckValves": "No",
              "PC_Scrubbers": "No",
              "PC_Flares": "No",
              "PC_ManualShutoffs": "No",
              "PC_AutomaticShutoffs": "No",
              "PC_Interlocks": "No",
              "PC_Alarms": "Yes",
              "PC_KeyedBypass": "No",
              "PC_EmergencyAirSupply": "No",
              "PC_EmergencyPower": "Yes",
              "PC_BackupPump": "No",
              "PC_GroundingEquipment": "No",
              "PC_InhibitorAddition": "No",
              "PC_RuptureDisks": "No",
              "PC_ExcessFlowDevice": "No",
              "PC_QuenchSystem": "No",
              "PC_PurgeSystem": "No",
              "PC_None": "No",
              "PC_OtherType": "containment vessel, fusible plug",
              "MS_SprinklerSystem": "Yes",
              "MS_Dikes": "Yes",
              "MS_FireWalls": "Yes",
              "MS_BlastWalls": "No",
              "MS_DelugeSystem": "No",
              "MS_WaterCurtain": "No",
              "MS_Enclosure": "No",
              "MS_Neutralization": "No",
              "MS_None": "No",
              "MS_OtherType": "Containment Vessel",
              "MD_ProcessAreaDetectors": "Yes",
              "MD_PerimeterMonitors": "No",
              "MD_None": "No",
              "MD_OtherType": "Life Safety System",
              "CH_ChemicalReduction": "No",
              "CH_ChemicalIncrease": "No",
              "CH_ChangeProcessParameters": "No",
              "CH_InstallProcessControls": "No",
              "CH_InstallProcessDetection": "No",
              "CH_InstallPerimeterMonitoring": "No",
              "CH_InstallMitigationSystems": "No",
              "CH_NoneRequired": "No",
              "CH_None": "Yes",
              "CH_OtherChanges": null,
              "OpProceduresReviewDate": "2022-12-14 00:00:00",
              "TrainingReviewDate": "2022-10-20 00:00:00",
              "TR_Classroom": "Yes",
              "TR_OnTheJob": "Yes",
              "TR_OtherType": "Intranet",
              "CT_WrittenTest": "Yes",
              "CT_OralTest": "No",
              "CT_Demonstration": "No",
              "CT_Observation": "Yes",
              "CT_OtherType": null,
              "MaintenanceReviewDate": "2022-10-20 00:00:00",
              "EquipmentInspectionDate": "2023-06-21 00:00:00",
              "EquipmentTested": "Gas detectors",
              "ChangeMgmtDate": "2020-02-14 00:00:00",
              "ChangeMgmtReviewDate": "2021-11-01 00:00:00",
              "PreStartupReviewDate": "2021-12-01 00:00:00",
              "ComplianceAuditDate": "2021-11-01 00:00:00",
              "AuditCompletionDate": "2023-05-24 00:00:00",
              "IncidentInvestigationDate": "2014-09-23 00:00:00",
              "InvestigationChangeDate": "2014-10-09 00:00:00",
              "ParticipationPlansReviewDate": "2021-11-01 00:00:00",
              "HotWorkPermitReviewDate": "2021-11-01 00:00:00",
              "ContractorSafetyReviewDate": "2023-01-17 00:00:00",
              "ContractorSafetyEvalDate": "2021-11-01 00:00:00",
              "CBI_Flag": "No",
              "Description": null,
              "_chemicals": [
                {
                  "PrimaryKey": 1000145205,
                  "PreventionProgram3ID": 1000115750,
                  "ProcessChemicalID": 1000168382
                }
              ]
            }
          ],
          "_prev_prog_2": []
        }
      ]
    },
    {
      "ProcessID": 1000134361,
      "AltID": "Bldg 5 AsH3 Cyl Storage",
      "FacilityID": 1000107465,
      "ProgramLevel": 3,
      "CBI_Flag": "No",
      "_chemicals": [
        {
          "ProcessChemicalID": 1000168383,
          "ProcessID": 1000134361,
          "ChemicalID": 67,
          "Quantity": 5100.0,
          "CBI_Flag": "No",
          "_flam_mix_chemicals": []
        }
      ],
      "_naics": [
        {
          "Process_NAICS_ID": 1000135776,
          "ProcessID": 1000134361,
          "NAICSCode": "32512",
          "_prev_prog_3": [
            {
              "PreventionProgram3ID": 1000115751,
              "Process_NAICS_ID": 1000135776,
              "SafetyReviewDate": "2023-09-06 00:00:00",
              "PHA_Date": "2023-02-07 00:00:00",
              "PHA_WhatIf": "Yes",
              "PHA_Checklist": "Yes",
              "PHA_WhatIfChecklist": "No",
              "PHA_HAZOP": "No",
              "PHA_FMEA": "No",
              "PHA_FTA": "No",
              "PHA_OtherTechnique": null,
              "PHACompletionDate": "2022-03-15 00:00:00",
              "MH_ToxicRelease": "Yes",
              "MH_Fire": "Yes",
              "MH_Explosion": "Yes",
              "MH_RunawayReaction": "No",
              "MH_Polymerization": "No",
              "MH_Overpressurization": "Yes",
              "MH_Corrosion": "Yes",
              "MH_Overfilling": "No",
              "MH_Contamination": "No",
              "MH_EquipmentFailure": "Yes",
              "MH_CoolingLoss": "Yes",
              "MH_Earthquake": "Yes",
              "MH_Floods": "No",
              "MH_Tornado": "No",
              "MH_Hurricanes": "No",
              "MH_OtherType": null,
              "PC_Vents": "No",
              "PC_ReliefValves": "No",
              "PC_CheckValves": "No",
              "PC_Scrubbers": "No",
              "PC_Flares": "No",
              "PC_ManualShutoffs": "No",
              "PC_AutomaticShutoffs": "No",
              "PC_Interlocks": "No",
              "PC_Alarms": "Yes",
              "PC_KeyedBypass": "No",
              "PC_EmergencyAirSupply": "No",
              "PC_EmergencyPower": "Yes",
              "PC_BackupPump": "No",
              "PC_GroundingEquipment": "No",
              "PC_InhibitorAddition": "No",
              "PC_RuptureDisks": "No",
              "PC_ExcessFlowDevice": "No",
              "PC_QuenchSystem": "No",
              "PC_PurgeSystem": "No",
              "PC_None": "No",
              "PC_OtherType": "containment vessel, fusible plug",
              "MS_SprinklerSystem": "Yes",
              "MS_Dikes": "Yes",
              "MS_FireWalls": "Yes",
              "MS_BlastWalls": "No",
              "MS_DelugeSystem": "No",
              "MS_WaterCurtain": "No",
              "MS_Enclosure": "No",
              "MS_Neutralization": "No",
              "MS_None": "No",
              "MS_OtherType": "Canopy, containment vessel",
              "MD_ProcessAreaDetectors": "Yes",
              "MD_PerimeterMonitors": "No",
              "MD_None": "No",
              "MD_OtherType": "Life Safety System",
              "CH_ChemicalReduction": "No",
              "CH_ChemicalIncrease": "No",
              "CH_ChangeProcessParameters": "No",
              "CH_InstallProcessControls": "No",
              "CH_InstallProcessDetection": "No",
              "CH_InstallPerimeterMonitoring": "No",
              "CH_InstallMitigationSystems": "No",
              "CH_NoneRequired": "No",
              "CH_None": "Yes",
              "CH_OtherChanges": null,
              "OpProceduresReviewDate": "2022-12-14 00:00:00",
              "TrainingReviewDate": "2022-10-20 00:00:00",
              "TR_Classroom": "Yes",
              "TR_OnTheJob": "Yes",
              "TR_OtherType": "Intranet",
              "CT_WrittenTest": "Yes",
              "CT_OralTest": "No",
              "CT_Demonstration": "No",
              "CT_Observation": "Yes",
              "CT_OtherType": null,
              "MaintenanceReviewDate": "2022-10-20 00:00:00",
              "EquipmentInspectionDate": "2023-06-21 00:00:00",
              "EquipmentTested": "Gas detectors",
              "ChangeMgmtDate": "2020-02-14 00:00:00",
              "ChangeMgmtReviewDate": "2021-11-01 00:00:00",
              "PreStartupReviewDate": "2021-12-01 00:00:00",
              "ComplianceAuditDate": "2021-11-01 00:00:00",
              "AuditCompletionDate": "2023-05-24 00:00:00",
              "IncidentInvestigationDate": "2014-09-23 00:00:00",
              "InvestigationChangeDate": "2014-10-09 00:00:00",
              "ParticipationPlansReviewDate": "2021-11-01 00:00:00",
              "HotWorkPermitReviewDate": "2021-11-01 00:00:00",
              "ContractorSafetyReviewDate": "2023-01-17 00:00:00",
              "ContractorSafetyEvalDate": "2021-11-01 00:00:00",
              "CBI_Flag": "No",
              "Description": null,
              "_chemicals": [
                {
                  "PrimaryKey": 1000145206,
                  "PreventionProgram3ID": 1000115751,
                  "ProcessChemicalID": 1000168383
                }
              ]
            }
          ],
          "_prev_prog_2": []
        }
      ]
    },
    {
      "ProcessID": 1000134362,
      "AltID": "Bldg 7 HCl Storage",
      "FacilityID": 1000107465,
      "ProgramLevel": 3,
      "CBI_Flag": "No",
      "_chemicals": [
        {
          "ProcessChemicalID": 1000168384,
          "ProcessID": 1000134362,
          "ChemicalID": 54,
          "Quantity": 7000.0,
          "CBI_Flag": "No",
          "_flam_mix_chemicals": []
        }
      ],
      "_naics": [
        {
          "Process_NAICS_ID": 1000135777,
          "ProcessID": 1000134362,
          "NAICSCode": "32512",
          "_prev_prog_3": [
            {
              "PreventionProgram3ID": 1000115752,
              "Process_NAICS_ID": 1000135777,
              "SafetyReviewDate": "2023-09-06 00:00:00",
              "PHA_Date": "2023-02-07 00:00:00",
              "PHA_WhatIf": "Yes",
              "PHA_Checklist": "Yes",
              "PHA_WhatIfChecklist": "No",
              "PHA_HAZOP": "No",
              "PHA_FMEA": "No",
              "PHA_FTA": "No",
              "PHA_OtherTechnique": null,
              "PHACompletionDate": "2022-03-15 00:00:00",
              "MH_ToxicRelease": "Yes",
              "MH_Fire": "Yes",
              "MH_Explosion": "Yes",
              "MH_RunawayReaction": "No",
              "MH_Polymerization": "No",
              "MH_Overpressurization": "Yes",
              "MH_Corrosion": "Yes",
              "MH_Overfilling": "No",
              "MH_Contamination": "No",
              "MH_EquipmentFailure": "Yes",
              "MH_CoolingLoss": "Yes",
              "MH_Earthquake": "Yes",
              "MH_Floods": "No",
              "MH_Tornado": "No",
              "MH_Hurricanes": "No",
              "MH_OtherType": null,
              "PC_Vents": "No",
              "PC_ReliefValves": "No",
              "PC_CheckValves": "No",
              "PC_Scrubbers": "No",
              "PC_Flares": "No",
              "PC_ManualShutoffs": "No",
              "PC_AutomaticShutoffs": "No",
              "PC_Interlocks": "No",
              "PC_Alarms": "Yes",
              "PC_KeyedBypass": "No",
              "PC_EmergencyAirSupply": "No",
              "PC_EmergencyPower": "Yes",
              "PC_BackupPump": "No",
              "PC_GroundingEquipment": "No",
              "PC_InhibitorAddition": "No",
              "PC_RuptureDisks": "No",
              "PC_ExcessFlowDevice": "No",
              "PC_QuenchSystem": "No",
              "PC_PurgeSystem": "No",
              "PC_None": "No",
              "PC_OtherType": "containment vessel, fusible plug",
              "MS_SprinklerSystem": "Yes",
              "MS_Dikes": "Yes",
              "MS_FireWalls": "Yes",
              "MS_BlastWalls": "No",
              "MS_DelugeSystem": "No",
              "MS_WaterCurtain": "No",
              "MS_Enclosure": "No",
              "MS_Neutralization": "No",
              "MS_None": "No",
              "MS_OtherType": "Canopy; Containment Vessel",
              "MD_ProcessAreaDetectors": "Yes",
              "MD_PerimeterMonitors": "No",
              "MD_None": "No",
              "MD_OtherType": "Life Safety System",
              "CH_ChemicalReduction": "No",
              "CH_ChemicalIncrease": "No",
              "CH_ChangeProcessParameters": "No",
              "CH_InstallProcessControls": "No",
              "CH_InstallProcessDetection": "No",
              "CH_InstallPerimeterMonitoring": "No",
              "CH_InstallMitigationSystems": "No",
              "CH_NoneRequired": "No",
              "CH_None": "Yes",
              "CH_OtherChanges": null,
              "OpProceduresReviewDate": "2022-12-14 00:00:00",
              "TrainingReviewDate": "2022-10-20 00:00:00",
              "TR_Classroom": "Yes",
              "TR_OnTheJob": "Yes",
              "TR_OtherType": "Intranet",
              "CT_WrittenTest": "Yes",
              "CT_OralTest": "No",
              "CT_Demonstration": "No",
              "CT_Observation": "Yes",
              "CT_OtherType": null,
              "MaintenanceReviewDate": "2022-10-20 00:00:00",
              "EquipmentInspectionDate": "2023-06-21 00:00:00",
              "EquipmentTested": "Gas detectors",
              "ChangeMgmtDate": "2020-02-14 00:00:00",
              "ChangeMgmtReviewDate": "2021-11-01 00:00:00",
              "PreStartupReviewDate": "2021-12-01 00:00:00",
              "ComplianceAuditDate": "2021-11-01 00:00:00",
              "AuditCompletionDate": "2023-05-24 00:00:00",
              "IncidentInvestigationDate": "2014-09-23 00:00:00",
              "InvestigationChangeDate": "2014-10-09 00:00:00",
              "ParticipationPlansReviewDate": "2021-11-01 00:00:00",
              "HotWorkPermitReviewDate": "2021-11-01 00:00:00",
              "ContractorSafetyReviewDate": "2023-01-17 00:00:00",
              "ContractorSafetyEvalDate": "2021-11-01 00:00:00",
              "CBI_Flag": "No",
              "Description": null,
              "_chemicals": [
                {
                  "PrimaryKey": 1000145207,
                  "PreventionProgram3ID": 1000115752,
                  "ProcessChemicalID": 1000168384
                }
              ]
            }
          ],
          "_prev_prog_2": []
        }
      ]
    },
    {
      "ProcessID": 1000134363,
      "AltID": "Bldg 7 SO2 Storage",
      "FacilityID": 1000107465,
      "ProgramLevel": 3,
      "CBI_Flag": "No",
      "_chemicals": [
        {
          "ProcessChemicalID": 1000168385,
          "ProcessID": 1000134363,
          "ChemicalID": 49,
          "Quantity": 25000.0,
          "CBI_Flag": "No",
          "_flam_mix_chemicals": []
        }
      ],
      "_naics": [
        {
          "Process_NAICS_ID": 1000135778,
          "ProcessID": 1000134363,
          "NAICSCode": "32512",
          "_prev_prog_3": [
            {
              "PreventionProgram3ID": 1000115753,
              "Process_NAICS_ID": 1000135778,
              "SafetyReviewDate": "2023-09-06 00:00:00",
              "PHA_Date": "2023-02-07 00:00:00",
              "PHA_WhatIf": "Yes",
              "PHA_Checklist": "Yes",
              "PHA_WhatIfChecklist": "No",
              "PHA_HAZOP": "No",
              "PHA_FMEA": "No",
              "PHA_FTA": "No",
              "PHA_OtherTechnique": null,
              "PHACompletionDate": "2022-03-15 00:00:00",
              "MH_ToxicRelease": "Yes",
              "MH_Fire": "Yes",
              "MH_Explosion": "Yes",
              "MH_RunawayReaction": "No",
              "MH_Polymerization": "No",
              "MH_Overpressurization": "Yes",
              "MH_Corrosion": "Yes",
              "MH_Overfilling": "No",
              "MH_Contamination": "No",
              "MH_EquipmentFailure": "Yes",
              "MH_CoolingLoss": "Yes",
              "MH_Earthquake": "Yes",
              "MH_Floods": "No",
              "MH_Tornado": "No",
              "MH_Hurricanes": "No",
              "MH_OtherType": null,
              "PC_Vents": "No",
              "PC_ReliefValves": "No",
              "PC_CheckValves": "No",
              "PC_Scrubbers": "No",
              "PC_Flares": "No",
              "PC_ManualShutoffs": "No",
              "PC_AutomaticShutoffs": "No",
              "PC_Interlocks": "No",
              "PC_Alarms": "Yes",
              "PC_KeyedBypass": "No",
              "PC_EmergencyAirSupply": "No",
              "PC_EmergencyPower": "Yes",
              "PC_BackupPump": "No",
              "PC_GroundingEquipment": "No",
              "PC_InhibitorAddition": "No",
              "PC_RuptureDisks": "No",
              "PC_ExcessFlowDevice": "No",
              "PC_QuenchSystem": "No",
              "PC_PurgeSystem": "No",
              "PC_None": "No",
              "PC_OtherType": "containment vessel, fusible plug",
              "MS_SprinklerSystem": "Yes",
              "MS_Dikes": "Yes",
              "MS_FireWalls": "Yes",
              "MS_BlastWalls": "No",
              "MS_DelugeSystem": "No",
              "MS_WaterCurtain": "No",
              "MS_Enclosure": "No",
              "MS_Neutralization": "No",
              "MS_None": "No",
              "MS_OtherType": "Canopy; Containment Vessel",
              "MD_ProcessAreaDetectors": "Yes",
              "MD_PerimeterMonitors": "No",
              "MD_None": "No",
              "MD_OtherType": "Life Safety System",
              "CH_ChemicalReduction": "No",
              "CH_ChemicalIncrease": "No",
              "CH_ChangeProcessParameters": "No",
              "CH_InstallProcessControls": "No",
              "CH_InstallProcessDetection": "No",
              "CH_InstallPerimeterMonitoring": "No",
              "CH_InstallMitigationSystems": "No",
              "CH_NoneRequired": "No",
              "CH_None": "Yes",
              "CH_OtherChanges": null,
              "OpProceduresReviewDate": "2022-12-14 00:00:00",
              "TrainingReviewDate": "2022-10-20 00:00:00",
              "TR_Classroom": "Yes",
              "TR_OnTheJob": "Yes",
              "TR_OtherType": "Intranet",
              "CT_WrittenTest": "Yes",
              "CT_OralTest": "No",
              "CT_Demonstration": "No",
              "CT_Observation": "Yes",
              "CT_OtherType": null,
              "MaintenanceReviewDate": "2022-10-20 00:00:00",
              "EquipmentInspectionDate": "2023-06-21 00:00:00",
              "EquipmentTested": "Gas detectors",
              "ChangeMgmtDate": "2020-02-14 00:00:00",
              "ChangeMgmtReviewDate": "2021-11-01 00:00:00",
              "PreStartupReviewDate": "2021-12-01 00:00:00",
              "ComplianceAuditDate": "2021-11-01 00:00:00",
              "AuditCompletionDate": "2023-05-24 00:00:00",
              "IncidentInvestigationDate": "2014-09-23 00:00:00",
              "InvestigationChangeDate": "2014-10-09 00:00:00",
              "ParticipationPlansReviewDate": "2021-11-01 00:00:00",
              "HotWorkPermitReviewDate": "2021-11-01 00:00:00",
              "ContractorSafetyReviewDate": "2023-01-17 00:00:00",
              "ContractorSafetyEvalDate": "2021-11-01 00:00:00",
              "CBI_Flag": "No",
              "Description": null,
              "_chemicals": [
                {
                  "PrimaryKey": 1000145208,
                  "PreventionProgram3ID": 1000115753,
                  "ProcessChemicalID": 1000168385
                }
              ]
            }
          ],
          "_prev_prog_2": []
        }
      ]
    },
    {
      "ProcessID": 1000134364,
      "AltID": "Bldg 5 Cl3HSi Storage",
      "FacilityID": 1000107465,
      "ProgramLevel": 3,
      "CBI_Flag": "No",
      "_chemicals": [
        {
          "ProcessChemicalID": 1000168386,
          "ProcessID": 1000134364,
          "ChemicalID": 153,
          "Quantity": 15000.0,
          "CBI_Flag": "No",
          "_flam_mix_chemicals": []
        }
      ],
      "_naics": [
        {
          "Process_NAICS_ID": 1000135779,
          "ProcessID": 1000134364,
          "NAICSCode": "32512",
          "_prev_prog_3": [
            {
              "PreventionProgram3ID": 1000115742,
              "Process_NAICS_ID": 1000135779,
              "SafetyReviewDate": "2023-09-06 00:00:00",
              "PHA_Date": "2023-02-07 00:00:00",
              "PHA_WhatIf": "Yes",
              "PHA_Checklist": "Yes",
              "PHA_WhatIfChecklist": "No",
              "PHA_HAZOP": "No",
              "PHA_FMEA": "No",
              "PHA_FTA": "No",
              "PHA_OtherTechnique": null,
              "PHACompletionDate": "2022-03-15 00:00:00",
              "MH_ToxicRelease": "Yes",
              "MH_Fire": "Yes",
              "MH_Explosion": "Yes",
              "MH_RunawayReaction": "No",
              "MH_Polymerization": "No",
              "MH_Overpressurization": "Yes",
              "MH_Corrosion": "Yes",
              "MH_Overfilling": "No",
              "MH_Contamination": "No",
              "MH_EquipmentFailure": "Yes",
              "MH_CoolingLoss": "Yes",
              "MH_Earthquake": "Yes",
              "MH_Floods": "No",
              "MH_Tornado": "No",
              "MH_Hurricanes": "No",
              "MH_OtherType": null,
              "PC_Vents": "No",
              "PC_ReliefValves": "No",
              "PC_CheckValves": "No",
              "PC_Scrubbers": "No",
              "PC_Flares": "No",
              "PC_ManualShutoffs": "No",
              "PC_AutomaticShutoffs": "No",
              "PC_Interlocks": "No",
              "PC_Alarms": "Yes",
              "PC_KeyedBypass": "No",
              "PC_EmergencyAirSupply": "No",
              "PC_EmergencyPower": "Yes",
              "PC_BackupPump": "No",
              "PC_GroundingEquipment": "No",
              "PC_InhibitorAddition": "No",
              "PC_RuptureDisks": "No",
              "PC_ExcessFlowDevice": "No",
              "PC_QuenchSystem": "No",
              "PC_PurgeSystem": "No",
              "PC_None": "No",
              "PC_OtherType": "containment vessel, fusible plug",
              "MS_SprinklerSystem": "Yes",
              "MS_Dikes": "Yes",
              "MS_FireWalls": "Yes",
              "MS_BlastWalls": "No",
              "MS_DelugeSystem": "No",
              "MS_WaterCurtain": "No",
              "MS_Enclosure": "No",
              "MS_Neutralization": "No",
              "MS_None": "No",
              "MS_OtherType": "Canopy, containment vessel",
              "MD_ProcessAreaDetectors": "Yes",
              "MD_PerimeterMonitors": "No",
              "MD_None": "No",
              "MD_OtherType": "Life Safety System",
              "CH_ChemicalReduction": "No",
              "CH_ChemicalIncrease": "No",
              "CH_ChangeProcessParameters": "No",
              "CH_InstallProcessControls": "No",
              "CH_InstallProcessDetection": "No",
              "CH_InstallPerimeterMonitoring": "No",
              "CH_InstallMitigationSystems": "No",
              "CH_NoneRequired": "No",
              "CH_None": "Yes",
              "CH_OtherChanges": null,
              "OpProceduresReviewDate": "2022-12-14 00:00:00",
              "TrainingReviewDate": "2022-10-20 00:00:00",
              "TR_Classroom": "Yes",
              "TR_OnTheJob": "Yes",
              "TR_OtherType": "Intranet",
              "CT_WrittenTest": "Yes",
              "CT_OralTest": "No",
              "CT_Demonstration": "No",
              "CT_Observation": "Yes",
              "CT_OtherType": null,
              "MaintenanceReviewDate": "2022-10-20 00:00:00",
              "EquipmentInspectionDate": "2023-06-21 00:00:00",
              "EquipmentTested": "Gas detectors",
              "ChangeMgmtDate": "2020-02-14 00:00:00",
              "ChangeMgmtReviewDate": "2021-11-01 00:00:00",
              "PreStartupReviewDate": "2021-12-01 00:00:00",
              "ComplianceAuditDate": "2021-11-01 00:00:00",
              "AuditCompletionDate": "2023-05-24 00:00:00",
              "IncidentInvestigationDate": "2014-09-23 00:00:00",
              "InvestigationChangeDate": "2014-10-09 00:00:00",
              "ParticipationPlansReviewDate": "2021-11-01 00:00:00",
              "HotWorkPermitReviewDate": "2021-11-01 00:00:00",
              "ContractorSafetyReviewDate": "2023-01-17 00:00:00",
              "ContractorSafetyEvalDate": "2021-11-01 00:00:00",
              "CBI_Flag": "No",
              "Description": null,
              "_chemicals": [
                {
                  "PrimaryKey": 1000145209,
                  "PreventionProgram3ID": 1000115742,
                  "ProcessChemicalID": 1000168386
                }
              ]
            }
          ],
          "_prev_prog_2": []
        }
      ]
    },
    {
      "ProcessID": 1000134365,
      "AltID": "Area 8 Propane Storage",
      "FacilityID": 1000107465,
      "ProgramLevel": 3,
      "CBI_Flag": "No",
      "_chemicals": [
        {
          "ProcessChemicalID": 1000168387,
          "ProcessID": 1000134365,
          "ChemicalID": 98,
          "Quantity": 20000.0,
          "CBI_Flag": "No",
          "_flam_mix_chemicals": []
        }
      ],
      "_naics": [
        {
          "Process_NAICS_ID": 1000135780,
          "ProcessID": 1000134365,
          "NAICSCode": "32512",
          "_prev_prog_3": [
            {
              "PreventionProgram3ID": 1000115743,
              "Process_NAICS_ID": 1000135780,
              "SafetyReviewDate": "2023-09-06 00:00:00",
              "PHA_Date": "2023-02-07 00:00:00",
              "PHA_WhatIf": "Yes",
              "PHA_Checklist": "Yes",
              "PHA_WhatIfChecklist": "No",
              "PHA_HAZOP": "No",
              "PHA_FMEA": "No",
              "PHA_FTA": "No",
              "PHA_OtherTechnique": null,
              "PHACompletionDate": "2022-03-15 00:00:00",
              "MH_ToxicRelease": "Yes",
              "MH_Fire": "Yes",
              "MH_Explosion": "Yes",
              "MH_RunawayReaction": "No",
              "MH_Polymerization": "No",
              "MH_Overpressurization": "Yes",
              "MH_Corrosion": "Yes",
              "MH_Overfilling": "No",
              "MH_Contamination": "No",
              "MH_EquipmentFailure": "Yes",
              "MH_CoolingLoss": "Yes",
              "MH_Earthquake": "Yes",
              "MH_Floods": "No",
              "MH_Tornado": "No",
              "MH_Hurricanes": "No",
              "MH_OtherType": null,
              "PC_Vents": "No",
              "PC_ReliefValves": "Yes",
              "PC_CheckValves": "No",
              "PC_Scrubbers": "No",
              "PC_Flares": "No",
              "PC_ManualShutoffs": "No",
              "PC_AutomaticShutoffs": "No",
              "PC_Interlocks": "No",
              "PC_Alarms": "Yes",
              "PC_KeyedBypass": "No",
              "PC_EmergencyAirSupply": "No",
              "PC_EmergencyPower": "Yes",
              "PC_BackupPump": "No",
              "PC_GroundingEquipment": "No",
              "PC_InhibitorAddition": "No",
              "PC_RuptureDisks": "No",
              "PC_ExcessFlowDevice": "No",
              "PC_QuenchSystem": "No",
              "PC_PurgeSystem": "No",
              "PC_None": "No",
              "PC_OtherType": "Containment vessel",
              "MS_SprinklerSystem": "Yes",
              "MS_Dikes": "Yes",
              "MS_FireWalls": "Yes",
              "MS_BlastWalls": "No",
              "MS_DelugeSystem": "No",
              "MS_WaterCurtain": "No",
              "MS_Enclosure": "No",
              "MS_Neutralization": "No",
              "MS_None": "No",
              "MS_OtherType": "Canopy, containment vessel",
              "MD_ProcessAreaDetectors": "Yes",
              "MD_PerimeterMonitors": "No",
              "MD_None": "No",
              "MD_OtherType": "Life Safety System",
              "CH_ChemicalReduction": "No",
              "CH_ChemicalIncrease": "No",
              "CH_ChangeProcessParameters": "No",
              "CH_InstallProcessControls": "No",
              "CH_InstallProcessDetection": "No",
              "CH_InstallPerimeterMonitoring": "No",
              "CH_InstallMitigationSystems": "No",
              "CH_NoneRequired": "No",
              "CH_None": "Yes",
              "CH_OtherChanges": null,
              "OpProceduresReviewDate": "2022-12-14 00:00:00",
              "TrainingReviewDate": "2022-10-20 00:00:00",
              "TR_Classroom": "Yes",
              "TR_OnTheJob": "Yes",
              "TR_OtherType": "Intranet",
              "CT_WrittenTest": "Yes",
              "CT_OralTest": "No",
              "CT_Demonstration": "No",
              "CT_Observation": "Yes",
              "CT_OtherType": null,
              "MaintenanceReviewDate": "2022-10-20 00:00:00",
              "EquipmentInspectionDate": "2023-06-21 00:00:00",
              "EquipmentTested": "Gas detectors",
              "ChangeMgmtDate": "2020-02-14 00:00:00",
              "ChangeMgmtReviewDate": "2021-11-01 00:00:00",
              "PreStartupReviewDate": "2021-12-01 00:00:00",
              "ComplianceAuditDate": "2021-11-01 00:00:00",
              "AuditCompletionDate": "2023-05-24 00:00:00",
              "IncidentInvestigationDate": "2014-09-23 00:00:00",
              "InvestigationChangeDate": "2014-10-09 00:00:00",
              "ParticipationPlansReviewDate": "2021-11-01 00:00:00",
              "HotWorkPermitReviewDate": "2021-11-01 00:00:00",
              "ContractorSafetyReviewDate": "2023-01-17 00:00:00",
              "ContractorSafetyEvalDate": "2021-11-01 00:00:00",
              "CBI_Flag": "No",
              "Description": null,
              "_chemicals": [
                {
                  "PrimaryKey": 1000145210,
                  "PreventionProgram3ID": 1000115743,
                  "ProcessChemicalID": 1000168387
                }
              ]
            }
          ],
          "_prev_prog_2": []
        }
      ]
    },
    {
      "ProcessID": 1000134366,
      "AltID": "Bldg 5 BCl3 Storage",
      "FacilityID": 1000107465,
      "ProgramLevel": 3,
      "CBI_Flag": "No",
      "_chemicals": [
        {
          "ProcessChemicalID": 1000168388,
          "ProcessID": 1000134366,
          "ChemicalID": 73,
          "Quantity": 5500.0,
          "CBI_Flag": "No",
          "_flam_mix_chemicals": []
        }
      ],
      "_naics": [
        {
          "Process_NAICS_ID": 1000135781,
          "ProcessID": 1000134366,
          "NAICSCode": "32512",
          "_prev_prog_3": [
            {
              "PreventionProgram3ID": 1000115739,
              "Process_NAICS_ID": 1000135781,
              "SafetyReviewDate": "2023-09-06 00:00:00",
              "PHA_Date": "2023-02-07 00:00:00",
              "PHA_WhatIf": "Yes",
              "PHA_Checklist": "Yes",
              "PHA_WhatIfChecklist": "No",
              "PHA_HAZOP": "No",
              "PHA_FMEA": "No",
              "PHA_FTA": "No",
              "PHA_OtherTechnique": null,
              "PHACompletionDate": "2022-03-15 00:00:00",
              "MH_ToxicRelease": "Yes",
              "MH_Fire": "Yes",
              "MH_Explosion": "Yes",
              "MH_RunawayReaction": "No",
              "MH_Polymerization": "No",
              "MH_Overpressurization": "Yes",
              "MH_Corrosion": "Yes",
              "MH_Overfilling": "No",
              "MH_Contamination": "No",
              "MH_EquipmentFailure": "Yes",
              "MH_CoolingLoss": "Yes",
              "MH_Earthquake": "Yes",
              "MH_Floods": "No",
              "MH_Tornado": "No",
              "MH_Hurricanes": "No",
              "MH_OtherType": null,
              "PC_Vents": "No",
              "PC_ReliefValves": "Yes",
              "PC_CheckValves": "No",
              "PC_Scrubbers": "No",
              "PC_Flares": "No",
              "PC_ManualShutoffs": "No",
              "PC_AutomaticShutoffs": "No",
              "PC_Interlocks": "No",
              "PC_Alarms": "Yes",
              "PC_KeyedBypass": "No",
              "PC_EmergencyAirSupply": "No",
              "PC_EmergencyPower": "Yes",
              "PC_BackupPump": "No",
              "PC_GroundingEquipment": "No",
              "PC_InhibitorAddition": "No",
              "PC_RuptureDisks": "No",
              "PC_ExcessFlowDevice": "No",
              "PC_QuenchSystem": "No",
              "PC_PurgeSystem": "No",
              "PC_None": "No",
              "PC_OtherType": "containment vessel, fusible plug",
              "MS_SprinklerSystem": "Yes",
              "MS_Dikes": "Yes",
              "MS_FireWalls": "Yes",
              "MS_BlastWalls": "No",
              "MS_DelugeSystem": "No",
              "MS_WaterCurtain": "No",
              "MS_Enclosure": "No",
              "MS_Neutralization": "No",
              "MS_None": "No",
              "MS_OtherType": "Canopy, containment vessel",
              "MD_ProcessAreaDetectors": "Yes",
              "MD_PerimeterMonitors": "No",
              "MD_None": "No",
              "MD_OtherType": "Life Safety System",
              "CH_ChemicalReduction": "No",
              "CH_ChemicalIncrease": "No",
              "CH_ChangeProcessParameters": "No",
              "CH_InstallProcessControls": "No",
              "CH_InstallProcessDetection": "No",
              "CH_InstallPerimeterMonitoring": "No",
              "CH_InstallMitigationSystems": "No",
              "CH_NoneRequired": "No",
              "CH_None": "Yes",
              "CH_OtherChanges": null,
              "OpProceduresReviewDate": "2022-12-14 00:00:00",
              "TrainingReviewDate": "2022-10-20 00:00:00",
              "TR_Classroom": "Yes",
              "TR_OnTheJob": "Yes",
              "TR_OtherType": "Intranet",
              "CT_WrittenTest": "Yes",
              "CT_OralTest": "No",
              "CT_Demonstration": "No",
              "CT_Observation": "Yes",
              "CT_OtherType": null,
              "MaintenanceReviewDate": "2022-10-20 00:00:00",
              "EquipmentInspectionDate": "2023-06-21 00:00:00",
              "EquipmentTested": "Gas detectors",
              "ChangeMgmtDate": "2020-02-14 00:00:00",
              "ChangeMgmtReviewDate": "2021-11-01 00:00:00",
              "PreStartupReviewDate": "2021-12-01 00:00:00",
              "ComplianceAuditDate": "2021-11-01 00:00:00",
              "AuditCompletionDate": "2023-05-24 00:00:00",
              "IncidentInvestigationDate": "2014-09-23 00:00:00",
              "InvestigationChangeDate": "2014-10-09 00:00:00",
              "ParticipationPlansReviewDate": "2021-11-01 00:00:00",
              "HotWorkPermitReviewDate": "2021-11-01 00:00:00",
              "ContractorSafetyReviewDate": "2023-01-17 00:00:00",
              "ContractorSafetyEvalDate": "2021-11-01 00:00:00",
              "CBI_Flag": "No",
              "Description": null,
              "_chemicals": [
                {
                  "PrimaryKey": 1000145211,
                  "PreventionProgram3ID": 1000115739,
                  "ProcessChemicalID": 1000168388
                }
              ]
            }
          ],
          "_prev_prog_2": []
        }
      ]
    }
  ],
  "_accidents": [],
  "_emerg_resp": {
    "FacilityID": 1000107465,
    "ER_CommunityPlan": "Yes",
    "ER_FacilityPlan": "No",
    "ER_ResponseActions": "No",
    "ER_PublicInfoProcedures": "No",
    "ER_EmergencyHealthCare": "No",
    "ER_ReviewDate": null,
    "ERTrainingDate": null,
    "CoordinatingAgencyName": "Alameda County Fire Department",
    "CoordinatingAgencyPhone": "5106183490",
    "FR_OSHA1910_38": "Yes",
    "FR_OSHA1910_120": "No",
    "FR_SPCC": "Yes",
    "FR_RCRA": "Yes",
    "FR_OPA90": "No",
    "FR_EPCRA": "Yes",
    "FR_OtherRegulation": null
  },
  "_exec_summary": [
    {
      "ESSeqNum": 5,
      "FacilityID": 1000107465,
      "SummaryText": "t and the SHE Contractor Questionnaire to Siemens for completion. Siemens provided the completed forms in May 2023. The forms are filed in the contractor binder.\n\nAll recommendations from past audits and PHA studies, as well as their implementation status, are included in Intelex or the PSM/RMP/CalARP - Forms / Records Volume."
    },
    {
      "ESSeqNum": 4,
      "FacilityID": 1000107465,
      "SummaryText": "ms annual internal audits to ensure the site is following the procedures and policies delineated in the facility's PSM/RMP/CalARP programs.  These audits have resulted in recommendations to improve safety at the facility, and the facility has proceeded with addressing and implementing these recommendations.  The facility utilizes a tracking system to ensure the recommendations are addressed in a timely manner.  Below is a sample of action items identified from previous audits that have been completed to improve safety at the facility:\n\n1) Contact the contractor that performs maintenance on the generator. Determine how long the generator is able to supply power to the life safety systems.\nActions Taken: According to the contractor (Power Plus), the tank has a capacity of 300 gallons (100%). At full capacity, the generator will be able to provide power for 20 hours at full load (meaning all equipment attached to the generator). At 150 gallons (50%), the generator will be able to provide power for 10.5 hours at full load.  \n\n2) Create an annual reminder on either Intelex, Master Control, or MS Outlook to invite the fire department onsite to coordinate emergency activities. In addition, utilize the Emergency Response Coordination Form (SHE-EM-103-F-13) to document the invitation and the meeting.\nActions Taken: The last drill was completed on 2/1/2023. The drill recap form was completed to document the drill. The fire department was involved (they came onsite). A rep from the fire department was notified about the drill but dispatch failed to notify fire department personnel so they ended up coming onsite as they thought it was an emergency. The annual reminder was created today on MS Outlook (the reminder pops up on February 1st of each year).\n\n3) Verify that the Contractor Selection Worksheet (SHE-SM-137-F-02) and the SHE Contractor Questionnaire (SHE-SM-137-F-01) have been completed for Siemens.\nActions Taken: The Site Manager emailed the Contractor Selection Workshee"
    },
    {
      "ESSeqNum": 3,
      "FacilityID": 1000107465,
      "SummaryText": "process.  The release must have caused at least one of the following:\n1) On-site deaths, injuries, or significant property damage (\u00a768.42(a)); or\n2) Known offsite deaths, injuries, property damage, environmental damage, evacuations, or sheltering in place (\u00a768.42(a)).\n\nA review of the facility's accident history showed that there have been no releases of regulated substances from the covered processes in the last five years that meet the above criteria.  In addition, there have been no releases of regulated substances that exceeded the Federal Reportable Quantity for each of the chemicals.\n\nEmergency Response Program\n\nAll regulated processes have been identified, located, and mapped. A cylinder storage procedure maintains consistent locations for each material.  Any changes in chemical storage locations are documented with the County of Alameda Department of Environmental Health in the facility's Hazardous Materials Business Plan.\n\nEvacuation procedures have been developed and all personnel are trained in the procedures. In addition, certain employees have been trained to assist the fire department in responding to a release if assistance is needed. The Emergency Response Contact List is maintained and all personnel are trained on the portions relevant to their job.\n\nPlanned Changes to Improve Safety\n\nMatheson Tri-Gas has made enhancements to improve safety at the facility.  For example, the facility has discontinued the use of the boron trichloride and chlorine purification processes, which were previously regulated under CalARP. The systems involved the processing of toxic and corrosive gases.  The chemicals have been removed from the systems, and the equipment has been shut down and properly isolated.  With the systems no longer in service, the likelihood of an accidental release as a result of equipment failure or human factor issues is significantly reduced, thereby improving the safety of the facility and the surrounding community.  \n\nMatheson Tri-Gas perfor"
    },
    {
      "ESSeqNum": 2,
      "FacilityID": 1000107465,
      "SummaryText": "d to identify the engineering and administrative controls in place to detect and mitigate the hazards. Recommendations are generated if the controls are found to be inadequate or non-existent.  These recommendations are then scheduled as process improvements. \n\nDevelopment and implementation of standard operating procedures: There is a system established for creating, reviewing, and maintaining operating procedures.  Written procedures have been established for the safe handling and storage of gas cylinders.\n\nDevelopment and implementation of accidental release prevention programs and facility safety programs: These programs have been developed in accordance with state and federal regulations.  They are reviewed annually to ensure they are properly implemented and records are maintained to support implementation.\n\nComprehensive training that includes classroom and on-the-job training:  Training has been established for new and existing employees such that safety in operations is maintained.\n\nA systematic preventive maintenance program: All relevant equipment is on a schedule for inspection. Inspections are documented and certain equipment are tested for proper operation on a regular schedule. \n\nA thorough accident reporting and investigation program: The accident/incident reporting and investigation procedure requires the reporting and investigation not only of incidents resulting in injuries, but also incidents that had the potential to result in an injury to an employee or a significant impact on the company's business.\n\nRestricted access: The facility has perimeter electronic gates that are always closed to restrict access into the facility. The facility is manned 24 hours a day, 7 days a week, 365 days a year. Cameras in the storage areas record all activities.\n\nFive-Year Accident History \n\nEPA's RMP Program defines accident as the following:\n\nThe release must be from a covered process and involve a regulated substance held above its threshold quantity in the"
    },
    {
      "ESSeqNum": 1,
      "FacilityID": 1000107465,
      "SummaryText": "-- Bldg 5 BCl3 Storage\nChlorine ------ Bldg 7 Cl2 Cylinder Storage\nChlorine ------ Bldg 5 Cl2 Cylinder Storage\nHydrogen Chloride ------ Bldg 7 HCl Cylinder Storage\nHydrogen Chloride ------ Bldg 5 HCl Cylinder Storage\nHydrogen Fluoride ------ Bldg 7 HF Cylinder Storage\nHydrogen Selenide ------ Bldg 5 H2Se Cylinder Storage\nPropane ----- Area 8 Cylinder Storage\nSulfur Dioxide ------ Bldg 7 SO2 Cylinder Storage\nTrichlorosilane ------ Bldg 7 HSiCl3 Cylinder Storage\nTrichlorosilane ------ Bldg 5 HSiCl3 Cylinder Storage\n\nAccidental Release Prevention Program and Mitigation Measures\n\nThe major elements of the Accidental Release Prevention Program and release mitigation measures at this site are as follows:  \n\nLife safety system: A life safety system was installed in late 1999. This system monitors the presence of various toxic and flammable gases in areas where those gases are stored. Two-stage alarms are set for each sensor. The low-level alarm alerts the facility that a problem may be developing. The high-level alarm triggers an evacuation of the building and provides notification to the Fire Department. The system provides real time readouts of gas concentrations and records all information. This information assists in preventing and mitigating gas releases.  \n\nAdherence to objective equipment standards: One of the most significant contributors to the prevention of accidental releases at this site is the high standard to which all gas cylinders must be manufactured. The Department of Transportation (DOT) and the National Fire Protection Association (NFPA) each have detailed requirements for the storage and handling of cylinders. Cylinders must be manufactured according to a particular metallurgical standard and be able to handle an increase in pressure, an increase in temperature, and the possibility that the cylinder will be hit or fall over.     \n\nProcess hazard analysis: Process hazard analyses are performed on the regulated processes to determine potential hazards an"
    },
    {
      "ESSeqNum": 0,
      "FacilityID": 1000107465,
      "SummaryText": "Executive Summary:\n\nNote:  This October 2023 update to the RMP was prepared to satisfy the five year update requirement.\n\nAccidental Release Prevention and Emergency Response Policies\n\nMatheson Tri-Gas is committed to developing and maintaining the manpower, the equipment, and the procedures necessary to prevent accidental releases of chemicals. In addition, we are committed to developing and maintaining the manpower, the equipment and the emergency response procedures necessary to mitigate a release quickly and effectively if it does occur. Employees and management meet regularly to discuss ongoing operations, potential problems, and continuous improvements to prevent releases from occurring. If needed, trained employees can provide assistance to outside emergency responders (fire department) in responding to a release or potential release.  \n\nStationary Source and Regulated Substances\n\nThe Matheson Tri-Gas facility is located at 6775 Central Avenue in Newark, California, which is approximately 1.1 miles southwest of Interstate 880.  The facility stores cylinders of compressed specialty/industrial gas in both large and small quantities. The cylinders vary from 2000 pounds to less than 1 pound of gas, depending on the size of the cylinder and the type of chemical packaged.  The cylinders remain at their respective storage location until purchased by a customer.\n\nThere are 10 chemicals in 15 processes at the Matheson Tri-Gas Newark facility that are regulated under the Federal RMP Program.  All regulated processes consist of cylinder storage only.  The detailed applicability of all chemicals, including inventory levels, is listed in the on-site California RMP (CalARP) documentation. The processes regulated under the federal RMP regulations can be summarized as follows:\n  \nChemical ------ Process\n\nAmmonia ------ Bldg 7 NH3 Storage\nAmmonia ------ Bldg 5 NH3 Storage\nArsine ----- Bldg 7 AsH3 Cylinder Storage\nArsine ----- Bldg 5 AsH3 Cylinder Storage\nBoron Trichloride ---"
    }
  ]
}